dumb_file_drop/__init__.py
dumb_file_drop/__main__.py
dumb_file_drop/templates/index.html
dumb_file_drop-0.1.1.dist-info/licenses/LICENSE.md
dumb_file_drop-0.1.1.dist-info/WHEEL
dumb_file_drop-0.1.1.dist-info/METADATA
dumb_file_drop-0.1.1.dist-info/RECORD
