Metadata-Version: 2.4
Name: dumb-file-drop
Version: 0.1.1
Summary: A simple webserver-based drop box which allows file uploads. Good for sending files to another device on your local network.
Keywords: dropbox
Author: Fastily
Author-email: Fastily <fastily@users.noreply.github.com>
License-Expression: GPL-3.0-or-later
License-File: LICENSE.md
Classifier: Natural Language :: English
Classifier: Programming Language :: Python :: 3
Classifier: Programming Language :: Python :: 3.9
Classifier: License :: OSI Approved :: GNU General Public License v3 (GPLv3)
Classifier: Operating System :: OS Independent
Requires-Dist: aiofiles
Requires-Dist: fastapi[all]
Requires-Dist: gunicorn
Requires-Dist: rich
Requires-Python: >=3.9
Project-URL: Bug Tracker, https://github.com/fastily/dumb-file-drop/issues
Project-URL: Homepage, https://github.com/fastily/dumb-file-drop
